<?xml version="1.0" encoding="UTF-8"?>
<!DOCTYPE plugin PUBLIC "-//JPF//Java Plug-in Manifest 1.0" "http://jpf.sourceforge.net/plugin_1_0.dtd">
<plugin id="com.equella.core3" version="1">
  <requires>
    <import plugin-id="com.equella.base" exported="true" />
    <import plugin-id="com.equella.serverbase" />
    <import plugin-id="com.tle.common.i18n" />
    <import plugin-id="com.tle.core.application" />
    <import plugin-id="com.tle.core.cluster" />
    <import plugin-id="com.tle.core.events" />
    <import plugin-id="com.tle.core.guice" />
    <import plugin-id="com.tle.core.hibernate" />
    <import plugin-id="com.tle.core.institution.convert" />
    <import plugin-id="com.tle.core.migration" />
    <import plugin-id="com.tle.core.security" />
    <import plugin-id="com.tle.core.services" />
    <import plugin-id="com.tle.core.zookeeper" />
    <import plugin-id="com.tle.platform.common" exported="true" />
    <import plugin-id="com.tle.platform.equella" />
  </requires>
  <extension plugin-id="com.tle.core.guice" point-id="module" id="guiceModules">
    <parameter id="class" value="com.tle.core.filesystem.guice.FilesystemModule" />
    <parameter id="class" value="com.tle.core.imagemagick.guice.ImageMagickModule" />
    <parameter id="class" value="com.tle.core.institution.convert.guice.InstitutionConverterTrackerModule" />
    <parameter id="class" value="com.tle.core.libav.guice.LibAvModule" />
    <parameter id="class" value="com.tle.core.scheduler.impl.SchedulerModule" />
    <parameter id="class" value="com.tle.core.services.guice.CoreServicesModule" />
    <parameter id="class" value="com.tle.core.services.guice.ServicesModule" />
    <parameter id="class" value="com.tle.core.settings.guice.ConfigModule" />
    <parameter id="class" value="com.tle.core.system.guice.DatabaseSchemaModule" />
  </extension>
  <extension plugin-id="com.tle.core.cluster" point-id="clusterMessageHandler" id="taskMessageHandler">
    <parameter id="bean" value="bean:com.tle.core.services.TaskService" />
  </extension>
  <extension plugin-id="com.tle.core.application" point-id="onStartup" id="checkMigrations">
    <parameter id="bean" value="bean:com.tle.core.migration.MigrationService" />
    <parameter id="type" value="core" />
    <parameter id="order" value="100" />
  </extension>
  <extension plugin-id="com.tle.core.events" point-id="applicationEventListener" id="listeners_6">
    <parameter id="listenerClass" value="com.tle.core.hibernate.event.SchemaListener" />
  </extension>
  <extension plugin-id="com.tle.core.migration" point-id="migration" id="initialSchema">
    <parameter id="id" value="com.tle.core.migration.initial.InitialSchema" />
    <parameter id="bean" value="bean:com.tle.core.migration.initial.InitialSchema" />
    <parameter id="initial" value="true" />
    <parameter id="date" value="1970-01-01" />
  </extension>
  <extension plugin-id="com.tle.core.migration" point-id="migration" id="itemsWithNullDateCreatedMigration">
    <parameter id="id" value="com.tle.core.migration.initial.ItemsWithNullDateCreatedMigration" />
    <parameter id="bean" value="bean:com.tle.core.migration.initial.ItemsWithNullDateCreatedMigration" />
    <parameter id="date" value="1970-01-01" />
  </extension>
  <extension plugin-id="com.tle.core.migration" point-id="migration" id="ensureUniqueGroupAndListPositionsMigration">
    <parameter id="id" value="com.tle.core.migration.initial.EnsureUniqueGroupAndListPositionsMigration" />
    <parameter id="date" value="1970-01-01" />
  </extension>
  <extension plugin-id="com.tle.core.migration" point-id="migration" id="couseListIndex">
    <parameter id="id" value="com.tle.core.migration.initial.AddCourseListIndex" />
    <parameter id="date" value="1970-01-01" />
  </extension>
  <extension plugin-id="com.tle.core.services" point-id="coreTasks" id="migrationGlobalTask">
    <parameter id="id" value="CheckSystemSchema" />
    <parameter id="essential" value="true" />
  </extension>
  <extension plugin-id="com.tle.core.services" point-id="coreTasks" id="schemaMigrationTask">
    <parameter id="id" value="MigrationTask*" />
    <parameter id="dependency" value="CheckSystemSchema" />
    <parameter id="essential" value="false" />
  </extension>
  <extension plugin-id="com.tle.core.institution.convert" point-id="converter" id="configurationConverter">
    <parameter id="id" value="CONFIGURATION" />
    <parameter id="class" value="bean:com.tle.core.settings.convert.ConfigurationConverter" />
    <parameter id="order" value="700" />
    <parameter id="selections">
      <parameter id="id" value="CONFIGURATION" />
      <parameter id="nameKey" value="institutions.tasks.configuration" />
    </parameter>
  </extension>
  <extension plugin-id="com.tle.core.events" point-id="applicationEventListener" id="listeners_5">
    <parameter id="listenerClass" value="com.tle.core.system.events.ServerMessageChangeListener" />
    <parameter id="listenerClass" value="com.tle.core.hibernate.event.SchemaListener" />
  </extension>
  <extension plugin-id="com.tle.core.hibernate" point-id="domainObjects" id="objects_4">
    <parameter id="factory" value="system" />
    <parameter id="class" value="com.tle.core.migration.beans.SystemConfig" />
    <parameter id="class" value="com.tle.beans.DatabaseSchema" />
  </extension>
  <extension plugin-id="com.tle.core.migration" point-id="migration" id="initialSystemMigration">
    <parameter id="id" value="com.tle.core.system.migration.InitialMigration" />
    <parameter id="bean" value="bean:com.tle.core.system.migration.InitialMigration" />
    <parameter id="system" value="true" />
    <parameter id="initial" value="true" />
    <parameter id="date" value="1970-01-01" />
  </extension>
  <extension plugin-id="com.tle.core.migration" point-id="migration" id="instIdMigration">
    <parameter id="id" value="com.tle.core.system.migration.InstitutionIdMigration" />
    <parameter id="bean" value="bean:com.tle.core.system.migration.InstitutionIdMigration" />
    <parameter id="date" value="1970-01-01" />
  </extension>
  <extension plugin-id="com.tle.core.hibernate" point-id="domainObjects" id="objects_3">
    <parameter id="class" value="com.tle.beans.ConfigurationProperty" />
  </extension>
  <extension plugin-id="com.tle.core.events" point-id="applicationEventListener" id="listeners_4">
    <parameter id="listenerClass" value="com.tle.core.settings.events.listeners.ConfigurationChangeListener" />
  </extension>
  <extension plugin-id="com.tle.core.security" point-id="securityTargetHandler" id="settingsTargetHandler">
    <parameter id="handlesLabellingFor" value="com.tle.common.security.SettingsTarget" />
    <parameter id="handler" value="bean:com.tle.core.settings.security.SettingsSecurityTargetHandler" />
  </extension>
  <extension plugin-id="com.tle.core.security" point-id="privilegeTreeProviders" id="systemConstantsPrivilegeTreeProvider">
    <parameter id="provider" value="bean:com.tle.core.settings.security.SettingsPrivilegeTreeProvider" />
  </extension>
  <extension plugin-id="com.tle.core.hibernate" point-id="domainObjects" id="objects_2">
    <parameter id="class" value="com.tle.beans.Institution" />
  </extension>
  <extension plugin-id="com.tle.core.events" point-id="applicationEventListener" id="listeners_3">
    <parameter id="listenerClass" value="com.tle.core.hibernate.event.SchemaListener" />
    <parameter id="listenerClass" value="com.tle.core.system.events.LicenseChangeListener" />
    <parameter id="listenerClass" value="com.tle.core.institution.events.listeners.InstitutionListener" />
  </extension>
  <extension plugin-id="com.tle.core.zookeeper" point-id="appServerExtension" id="clusterAppServerExt">
    <parameter id="bean" value="bean:com.tle.core.institution.ClusterInfoService" />
    <parameter id="order" value="700" />
  </extension>
  <extension plugin-id="com.tle.core.application" point-id="onStartup" id="registerIps">
    <parameter id="bean" value="bean:com.tle.core.institution.ClusterInfoService" />
    <parameter id="type" value="initial" />
    <parameter id="order" value="1000" />
  </extension>
  <extension plugin-id="com.tle.core.services" point-id="coreTasks" id="institutionsTask">
    <parameter id="id" value="InstitutionKeeper" />
    <parameter id="dependency" value="CheckSystemSchema" />
    <parameter id="essential" value="true" />
  </extension>
  <extension plugin-id="com.tle.core.events" point-id="eventExecutor" id="eventImpl">
    <parameter id="bean" value="bean:com.tle.core.events.EventExecutor" />
  </extension>
  <extension plugin-id="com.tle.core.events" point-id="applicationEventListener" id="listeners_2_2">
    <parameter id="listenerClass" value="com.tle.core.healthcheck.listeners.ServiceCheckRequestListener" />
  </extension>
  <extension plugin-id="com.tle.core.events" point-id="applicationEventListener" id="listeners_2">
    <parameter id="listenerClass" value="com.tle.core.healthcheck.listeners.ServiceCheckRequestListener" />
  </extension>
  <extension plugin-id="com.tle.core.hibernate" point-id="domainObjects" id="objects">
    <parameter id="class" value="com.tle.beans.Staging" />
  </extension>
  <extension plugin-id="com.tle.core.institution.convert" point-id="converter" id="migrationConverter">
    <parameter id="id" value="MIGRATION" />
    <parameter id="class" value="bean:com.tle.core.institution.convert.MigrationConverter" />
    <parameter id="order" value="100" />
  </extension>
  <extension plugin-id="com.tle.core.institution.convert" point-id="converter" id="zippingConverter">
    <parameter id="id" value="ZIPFILES" />
    <parameter id="class" value="bean:com.tle.core.institution.convert.ZippingConverter" />
    <parameter id="order" value="20000" />
  </extension>
  <extension plugin-id="com.tle.core.events" point-id="applicationEventListener" id="listeners">
    <parameter id="listenerClass" value="com.tle.core.hibernate.event.SchemaListener" />
    <parameter id="listenerClass" value="com.tle.core.institution.events.listeners.InstitutionListener" />
  </extension>
  <extension plugin-id="com.tle.core.zookeeper" point-id="appServerExtension" id="schedulerTaskStarter">
    <parameter id="bean" value="bean:com.tle.core.scheduler.SchedulerService" />
    <parameter id="order" value="1000" />
  </extension>
  <extension plugin-id="com.tle.core.services" point-id="coreTasks" id="schedulerTask">
    <parameter id="id" value="Scheduler-Supervisor" />
    <parameter id="dependency" value="CheckSystemSchema" />
    <parameter id="essential" value="false" />
  </extension>
  <extension plugin-id="com.tle.common.i18n" point-id="bundle" id="strings_resource-centre">
    <parameter id="group" value="resource-centre" />
    <parameter id="file" value="lang/i18n-resource-centre.properties" />
  </extension>
</plugin>
